Workbook

Sheet Dashboard
A1: Support Ticket Report — Dashboard
A4: Total Tickets | C4: Open Now | E4: Resolved / Closed | G4: Avg Hours to Resolve | I4: Data-Quality Issues
A5: 3,000 | C5: 465 | E5: 2,535 | G5: 47.3 | I5: 77

Sheet Raw Data (SQL export)
A1: TicketID | B1: CustomerID | C1: CategoryID | D1: AssignedAgentID | E1: Subject | F1: Priority | G1: Status | H1: CreatedAt | I1: ResolvedAt
A2: 1 | B2: 11 | C2: 1 | D2: 2 | E2: Historic orders disappeared from view | F2: Low | G2: Resolved | H2: 2026-06-25 06:55:00 | I2: 2026-06-30 11:41:52
A3: 2 | B3: 2 | C3: 5 | D3: 2 | E3: How do I add a new user? | F3: Medium | G3: Open | H3: 2025-09-09 06:23:00
A4: 3 | B4: 9 | C4: 2 | D4: 5 | E4: Search timing out during peak hours | F4: Low | G4: Closed | H4: 2025-09-11 00:22:00 | I4: 2025-09-17 02:55:54
A5: 4 | B5: 12 | C5: 4 | D5: 2 | E5: Need monthly sales report by region | F5: Medium | G5: Closed | H5: 2025-11-07 17:42:00 | I5: 2025-11-08 19:15:41
A6: 5 | B6: 6 | C6: 3 | D6: 6 | E6: Error 500 when saving a new order | F6: Medium | G6: Resolved | H6: 2026-01-01 21:10:00 | I6: 2026-01-02 07:54:16
A7: 6 | B7: 9 | C7: 3 | D7: 6 | E7: Error 500 when saving a new order | F7: High | G7: Closed | H7: 2025-10-23 03:59:00 | I7: 2025-10-23 20:11:32
A8: 7 | B8: 14 | C8: 2 | D8: 4 | E8: Search timing out during peak hours | F8: Medium | G8: Closed | H8: 2026-04-30 22:53:00 | I8: 2026-05-02 02:25:17
A9: 8 | B9: 11 | C9: 3 | D9: 2 | E9: Export button does nothing | F9: Medium | G9: Resolved | H9: 2026-05-22 12:10:00 | I9: 2026-05-23 07:18:12
A10: 9 | B10: 15 | C10: 5 | D10: 1 | E10: How to schedule an automatic export? | F10: Low | G10: Resolved | H10: 2026-02-03 13:57:00 | I10: 2026-02-03 23:12:51
A11: 10 | B11: 2 | C11: 2 | D11: 4 | E11: Report export extremely slow | F11: Low | G11: Closed | H11: 2025-11-26 08:37:00 | I11: 2025-12-02 18:36:08
A12: 11 | B12: 3 | C12: 2 | D12: 4 | E12: Search timing out during peak hours | F12: Medium | G12: Resolved | H12: 2026-01-03 04:16:00 | I12: 2026-01-04 10:13:28
A13: 12 | B13: 9 | C13: 4 | D13: 1 | E13: Quarterly summary for board pack | F13: Low | G13: Resolved | H13: 2026-05-08 07:15:00 | I13: 2026-05-09 13:29:13
A14: 13 | B14: 2 | C14: 4 | D14: 4 | E14: Need monthly sales report by region | F14: Medium | G14: Closed | H14: 2025-10-08 14:44:00 | I14: 2025-10-11 12:42:31
A15: 14 | B15: 11 | C15: 1 | D15: 3 | E15: Missing records in nightly sync | F15: High | G15: Resolved | H15: 2025-12-31 04:54:00 | I15: 2025-12-31 15:53:58
... A21: 20 | B21: 8 | C21: 1 | D21: 3 | E21: Import file rejected duplicate rows | F21: High | G21: Closed | H21: 2026-01-13 23:33:00 | I21: 2026-01-14 13:17:24
A22: 21 | B22: 2 | C22: 1 | D22: 3 | E22: Customer totals do not match invoice | F22: High | G22: Open | H22: 2026-01-27 18:58:00
A23: 22 | B23: 5 | C23: 4 | D23: 6 | E23: Add discount column to invoice report | F23: Medium | G23: Closed | H23: 2026-02-07 11:57:00 | I23: 2026-02-09 05:55:22
A24: 23 | B24: 13 | C24: 4 | D24: 3 | E24: Add discount column to invoice report | F24: Low | G24: In Progress | H24: 2026-02-24 20:21:00
A25: 24 | B25: 14 | C25: 1 | E25: Import file rejected duplicate rows | F25: Medium | G25: Open | H25: 2026-05-02 20:02:00
A26: 25 | B26: 4 | C26: 2 | D26: 2 | E26: Dashboard takes over a minute to load | F26: Low | G26: Closed | H26: 2026-02-24 23:52:00 | I26: 2026-02-27 01:32:53
A27: 26 | B27: 8 | C27: 5 | E27: How do I add a new user? | F27: Medium | G27: Open | H27: 2026-05-03 04:56:00
A28: 27 | B28: 15 | C28: 2 | D28: 4 | E28: System freezes when opening large accounts | F28: Low | G28: Closed | H28: 2026-03-14 09:31:00 | I28: 2026-03-17 07:17:14
A29: 28 | B29: 1 | C29: 4 | D29: 4 | E29: Quarterly summary for board pack | F29: Low | G29: Resolved | H29: 2026-01-01 09:15:00 | I29: 2026-01-06 07:29:27
A30: 29 | B30: 11 | C30: 4 | D30: 2 | E30: New KPI dashboard for finance team | F30: Medium | G30: Closed | H30: 2026-03-22 18:44:00 | I30: 2026-03-24 13:16:33
A31: 30 | B31: 1 | C31: 1 | D31: 5 | E31: Customer totals do not match invoice | F31: Low | G31: Closed | H31: 2025-07-31 07:32:00 | I31: 2025-08-07 01:06:03
A32: 31 | B32: 2 | C32: 5 | D32: 2 | E32: Can we bulk update product prices? | F32: Low | G32: Resolved | H32: 2026-05-25 00:18:00 | I32: 2026-05-31 14:43:18
A33: 32 | B33: 10 | C33: 1 | D33: 5 | E33: Missing records in nightly sync | F33: Medium | G33: Closed | H33: 2026-05-14 19:15:00 | I33: 2026-05-15 19:23:45
A34: 33 | B34: 4 | C34: 3 | D34: 4 | E34: Error 500 when saving a new order | F34: Low | G34: In Progress | H34: 2025-09-28 07:09:00
A35: 34 | B35: 1 | C35: 4 | D35: 3 | E35: New KPI dashboard for finance team | F35: High | G35: Open | H35: 2026-05-01 16:43:00
A36: 35 | B36: 15 | C36: 1 | D36: 2 | E36: Historic orders disappeared from view | F36: Low | G36: Closed | H36: 2026-01-16 14:50:00 | I36: 2026-01-20 11:55:15
A37: 36 | B37: 1 | C37: 5 | D37: 1 | E37: How do I add a new user? | F37: Medium | G37: Resolved | H37: 2025-12-07 11:59:00 | I37: 2025-12-07 23:23:01
A38: 37 | B38: 12 | C38: 5 | D38: 5 | E38: How to schedule an automatic export? | F38: Low | G38: Closed | H38: 2026-03-22 07:22:00 | I38: 2026-03-24 19:35:56
A39: 38 | B39: 9 | C39: 4 | D39: 1 | E39: Need monthly sales report by region | F39: High | G39: Resolved | H39: 2026-01-11 15:21:00 | I39: 2026-01-12 02:05:32
A40: 39 | B40: 6 | C40: 2 | D40: 4 | E40: Dashboard takes over a minute to load | F40: Medium | G40: Closed | H40: 2026-01-03 18:00:00
A41: 40 | B41: 15 | C41: 2 | D41: 5 | E41: Report export extremely slow | F41: Medium | G41: Resolved | H41: 2026-06-17 06:22:00 | I41: 2026-06-18 14:27:06
A42: 41 | B42: 15 | C42: 1 | D42: 2 | E42: Address data showing in wrong fields | F42: Medium | G42: Closed | H42: 2025-10-25 22:50:00 | I42: 2025-10-27 01:35:27
A43: 42 | B43: 10 | C43: 2 | D43: 2 | E43: Report export extremely slow | F43: Medium | G43: Resolved | H43: 2026-01-22 02:43:00 | I43: 2026-01-22 06:27:06
A44: 43 | B44: 13 | C44: 4 | D44: 6 | E44: Request custom stock level extract | F44: High | G44: Closed | H44: 2026-01-13 18:58:00 | I44: 2026-01-14 16:01:35
A45: 44 | B45: 4 | C45: 4 | D45: 2 | E45: New KPI dashboard for finance team | F45: Low | G45: Closed | H45: 2025-10-31 21:17:00 | I45: 2025-11-05 13:31:43
A46: 45 | B46: 14 | C46: 1 | D46: 5 | E46: Import file rejected duplicate rows | F46: Low | G46: Closed | H46: 2025-12-22 05:57:00 | I46: 2025-12-29 02:51:30
A47: 46 | B47: 2 | C47: 3 | D47: 3 | E47: Export button does nothing | F47: High | G47: Closed | H47: 2026-03-05 11:19:00 | I47: 2026-03-06 02:02:16
A48: 47 | B48: 7 | C48: 5 | D48: 5 | E48: Can we bulk update product prices? | F48: Low | G48: Closed | H48: 2026-04-20 06:57:00 | I48: 2026-04-20 18:13:45
A49: 48 | B49: 15 | C49: 5 | D49: 1 | E49: How do I add a new user? | F49: Medium | G49: Closed | H49: 2026-02-20 00:34:00 | I49: 2026-02-22 19:01:14
A50: 49 | B50: 12 | C50: 3 | D50: 3 | E50: Date picker shows wrong month | F50: Low | G50: Resolved | H50: 2025-11-30 06:52:00 | I50: 2025-12-02 11:21:14
A51: 50 | B51: 11 | C51: 4 | D51: 3 | E51: Request custom stock level extract | F51: Low | G51: Resolved | H51: 2026-03-08 18:40:00 | I51: 2026-03-14 15:23:51
A52: 51 | B52: 7 | C52: 5 | D52: 4 | E52: Where can I change my invoice template? | F52: Medium | G52: Closed | H52: 2025-11-20 20:18:00 | I52: 2025-11-22 10:04:55
... A65: 64 | B65: 2 | C65: 4 | D65: 2 | E65: New KPI dashboard for finance team | F65: High | G65: Resolved | H65: 2026-04-05 16:29:00 | I65: 2026-04-06 02:12:09
A66: 65 | B66: 6 | C66: 4 | D66: 4 | E66: Quarterly summary for board pack | F66: Low | G66: Resolved | H66: 2025-12-22 21:07:00
A67: 66 | B67: 1 | C67: 3 | D67: 6 | E67: Error 500 when saving a new order | F67: High | G67: Resolved | H67: 2026-01-31 05:27:00 | I67: 2026-01-31 07:09:49
A68: 67 | B68: 10 | C68: 2 | D68: 5 | E68: System freezes when opening large accounts | F68: Medium | G68: In Progress | H68: 2026-01-20 19:08:00
A69: 68 | B69: 12 | C69: 3 | D69: 5 | E69: Login page loops back to itself | F69: Medium | G69: Closed | H69: 2025-10-17 21:06:00 | I69: 2025-10-20 01:23:06
A70: 69 | B70: 5 | C70: 1 | D70: 5 | E70: Customer totals do not match invoice | F70: Medium | G70: Resolved | H70: 2026-06-24 19:15:00 | I70: 2026-06-27 16:19:19
A71: 70 | B71: 2 | C71: 5 | D71: 6 | E71: How do I add a new user? | F71: Medium | G71: In Progress | H71: 2026-01-17 15:54:00
A72: 71 | B72: 13 | C72: 5 | D72: 4 | E72: How do I add a new user? | F72: Medium | G72: Closed | H72: 2026-06-13 14:16:00 | I72: 2026-06-13 21:05:37
A73: 72 | B73: 14 | C73: 4 | E73: Add discount column to invoice report | F73: Medium | G73: In Progress | H73: 2025-07-21 13:07:00
A74: 73 | B74: 12 | C74: 2 | D74: 5 | E74: Batch job overrunning into business hours | F74: Medium | G74: Closed | H74: 2025-08-30 09:19:00 | I74: 2025-08-31 06:13:20
A75: 74 | B75: 13 | C75: 4 | D75: 6 | E75: Need monthly sales report by region | F75: Medium | G75: Closed | H75: 2025-08-08 23:45:00 | I75: 2025-08-10 00:18:40
A76: 75 | B76: 5 | C76: 4 | D76: 5 | E76: New KPI dashboard for finance team | F76: Medium | G76: Resolved | H76: 2026-01-16 22:11:00 | I76: 2026-01-18 02:42:45
A77: 76 | B77: 3 | C77: 4 | D77: 3 | E77: New KPI dashboard for finance team | F77: Low | G77: Closed | H77: 2026-02-09 00:57:00 | I77: 2026-02-15 05:19:20
A78: 77 | B78: 9 | C78: 1 | D78: 4 | E78: Customer totals do not match invoice | F78: Medium | G78: In Progress | H78: 2026-02-24 09:03:00
A79: 78 | B79: 12 | C79: 4 | D79: 1 | E79: New KPI dashboard for finance team | F79: High | G79: Closed | H79: 2025-07-21 02:17:00 | I79: 2025-07-21 08:22:48
A80: 79 | B80: 11 | C80: 5 | D80: 5 | E80: How to schedule an automatic export? | F80: Low | G80: Closed | H80: 2025-10-17 18:55:00 | I80: 2025-10-24 18:21:51
A81: 80 | B81: 12 | C81: 4 | D81: 2 | E81: Quarterly summary for board pack | F81: High | G81: Closed | H81: 2025-12-28 05:24:00 | I81: 2025-12-28 10:49:45
A82: 81 | B82: 13 | C82: 2 | D82: 4 | E82: Batch job overrunning into business hours | F82: Low | G82: Closed | H82: 2026-02-24 00:35:00 | I82: 2026-02-28 05:16:32
A83: 82 | B83: 5 | C83: 1 | D83: 3 | E83: Missing records in nightly sync | F83: Low | G83: Closed | H83: 2026-02-22 03:33:00 | I83: 2026-02-22 09:52:13
A84: 83 | B84: 1 | C84: 1 | D84: 2 | E84: Import file rejected duplicate rows | F84: Medium | G84: Resolved | H84: 2025-12-12 18:33:00 | I84: 2025-12-15 01:14:43
A85: 84 | B85: 10 | C85: 3 | D85: 3 | E85: Date picker shows wrong month | F85: Low | G85: Closed | H85: 2025-08-05 16:42:00 | I85: 2025-08-06 05:07:32
A86: 85 | B86: 2 | C86: 1 | D86: 5 | E86: Historic orders disappeared from view | F86: Medium | G86: Closed | H86: 2025-09-24 17:08:00 | I86: 2025-09-24 22:53:09
A87: 86 | B87: 5 | C87: 1 | D87: 5 | E87: Historic orders disappeared from view | F87: Medium | G87: In Progress | H87: 2026-01-13 18:33:00
A88: 87 | B88: 4 | C88: 5 | D88: 4 | E88: Can we bulk update product prices? | F88: Low | G88: Closed | H88: 2025-10-09 12:25:00 | I88: 2025-10-13 16:56:05
A89: 88 | B89: 10 | C89: 1 | D89: 2 | E89: Customer totals do not match invoice | F89: Medium | G89: Resolved | H89: 2026-05-02 05:47:00 | I89: 2026-05-03 02:18:30
A90: 89 | B90: 3 | C90: 5 | D90: 6 | E90: How to schedule an automatic export? | F90: Medium | G90: In Progress | H90: 2026-05-19 20:09:00
A91: 90 | B91: 1 | C91: 2 | D91: 6 | E91: Report export extremely slow | F91: Medium | G91: Resolved | H91: 2025-12-15 17:01:00 | I91: 2025-12-15 23:59:57
A92: 91 | B92: 13 | C92: 5 | D92: 5 | E92: Where can I change my invoice template? | F92: Low | G92: Closed | H92: 2026-02-19 10:52:00 | I92: 2026-02-20 15:18:03
A93: 92 | B93: 2 | C93: 1 | D93: 5 | E93: Import file rejected duplicate rows | F93: Medium | G93: Resolved | H93: 2026-03-14 16:18:00 | I93: 2026-03-16 10:08:40
A94: 93 | B94: 8 | C94: 3 | D94: 5 | E94: Date picker shows wrong month | F94: Medium | G94: Resolved | H94: 2025-09-23 09:40:00 | I94: 2025-09-24 18:18:35
A95: 94 | B95: 12 | C95: 3 | D95: 6 | E95: Email notifications not being sent | F95: Medium | G95: Open | H95: 2026-01-12 04:31:00
A96: 95 | B96: 10 | C96: 1 | D96: 2 | E96: Customer totals do not match invoice | F96: Medium | G96: Closed | H96: 2025-12-29 05:58:00 | I96: 2025-12-31 05:34:20
A97: 96 | B97: 10 | C97: 4 | D97: 4 | E97: Request custom stock level extract | F97: Low | G97: Resolved | H97: 2025-07-20 10:29:00 | I97: 2025-07-22 21:08:45
A98: 97 | B98: 6 | C98: 4 | D98: 4 | E98: New KPI dashboard for finance team | F98: Medium | G98: Closed | H98: 2025-07-17 17:04:00 | I98: 2025-07-19 09:34:24
A99: 98 | B99: 5 | C99: 3 | D99: 4 | E99: Email notifications not being sent | F99: Medium | G99: Resolved | H99: 2026-04-20 02:08:00
A100: 99 | B100: 8 | C100: 4 | D100: 3 | E100: Need monthly sales report by region | F100: Medium | G100: Closed | H100: 2026-06-04 00:43:00 | I100: 2026-06-05 13:36:40
A101: 100 | B101: 4 | C101: 3 | D101: 4 | E101: Email notifications not being sent | F101: Medium | G101: Resolved | H101: 2026-04-09 02:23:00 | I101: 2026-04-10 14:18:47
A102: 101 | B102: 13 | C102: 2 | D102: 1 | E102: Dashboard takes over a minute to load | F102: Medium | G102: Closed | H102: 2026-03-20 04:09:00 | I102: 2026-03-20 12:40:28
A103: 102 | B103: 8 | C103: 1 | D103: 6 | E103: Address data showing in wrong fields | F103: Low | G103: Closed | H103: 2026-03-23 09:10:00 | I103: 2026-03-28 08:51:15
A104: 103 | B104: 8 | C104: 2 | D104: 4 | E104: Search timing out during peak hours | F104: Low | G104: Closed | H104: 2025-08-14 21:05:00 | I104: 2025-08-19 03:22:52
A105: 104 | B105: 14 | C105: 1 | D105: 4 | E105: Import file rejected duplicate rows | F105: Low | G105: Resolved | H105: 2025-12-24 08:14:00 | I105: 2025-12-29 21:25:08
A106: 105 | B106: 5 | C106: 3 | D106: 4 | E106: Email notifications not being sent | F106: Medium | G106: Resolved | H106: 2025-07-21 22:55:00 | I106: 2025-07-23 01:04:31
A107: 106 | B107: 7 | C107: 4 | D107: 6 | E107: Add discount column to invoice report | F107: Low | G107: Resolved | H107: 2025-11-21 04:32:00 | I107: 2025-11-23 23:20:25
A108: 107 | B108: 1 | C108: 3 | D108: 4 | E108: Login page loops back to itself | F108: Low | G108: Resolved | H108: 2025-08-03 02:09:00 | I108: 2025-08-07 18:59:41
A109: 108 | B109: 8 | C109: 1 | D109: 5 | E109: Import file rejected duplicate rows | F109: Low | G109: Closed | H109: 2026-04-12 13:42:00 | I109: 2026-04-13 10:09:35
A110: 109 | B110: 9 | C110: 4 | D110: 4 | E110: New KPI dashboard for finance team | F110: Medium | G110: Resolved | H110: 2026-07-02 07:47:00 | I110: 2026-07-05 05:40:49
A111: 110 | B111: 6 | C111: 5 | D111: 3 | E111: How to schedule an automatic export? | F111: Medium | G111: Resolved | H111: 2025-09-27 01:29:00 | I111: 2025-09-29 15:38:14
... A118: 117 | B118: 14 | C118: 4 | D118: 5 | E118: Need monthly sales report by region | F118: Low | G118: Closed | H118: 2026-04-26 20:06:00 | I118: 2026-04-29 00:37:23
A119: 118 | B119: 14 | C119: 4 | E119: Need monthly sales report by region | F119: Medium | G119: Open | H119: 2025-12-25 15:07:00
A120: 119 | B120: 15 | C120: 5 | D120: 3 | E120: Where can I change my invoice template? | F120: Medium | G120: Resolved | H120: 2025-07-16 19:04:00 | I120: 2025-07-17 13:10:29
A121: 120 | B121: 11 | C121: 2 | D121: 6 | E121: Dashboard takes over a minute to load | F121: Medium | G121: Resolved | H121: 2026-01-11 23:59:00 | I121: 2026-01-14 01:38:35
A122: 121 | B122: 15 | C122: 1 | D122: 1 | E122: Missing records in nightly sync | F122: Medium | G122: Resolved | H122: 2025-11-30 13:01:00 | I122: 2025-12-02 18:16:54
A123: 122 | B123: 6 | C123: 4 | D123: 5 | E123: New KPI dashboard for finance team | F123: Medium | G123: Closed | H123: 2026-03-07 14:29:00 | I123: 2026-03-08 18:05:36
...

Sheet Cleaned Data
A1: TicketID | B1: Customer | C1: Tier | D1: Region | E1: Category | F1: Agent | G1: Team | H1: Priority | I1: Status | J1: CreatedDate | K1: Month | L1: ResolvedDate | M1: HoursToResolve | N1: IsResolved | O1: DataQualityFlag
A2: 1 | B2: Kite Energy | C2: Business | D2: UK & Ireland | E2: Data Issue | F2: James Whitfield | G2: Technical Services | H2: Low | I2: Resolved | J2: 46198.288 | K2: 2026-06 | L2: 46203.487 | M2: 124.8 | N2: 1
A3: 2 | B3: Bristol Logistics | C3: Business | D3: UK & Ireland | E3: How-To Question | F3: James Whitfield | G3: Technical Services | H3: Medium | I3: Open | J3: 45909.266 | K3: 2025-09 | N3: 0 | O3: Open > 30 days
A4: 3 | B4: Iris Insurance | C4: Business | D4: EMEA | E4: Performance | F4: Sofia Lindqvist | G4: Service Desk | H4: Low | I4: Closed | J4: 45911.015 | K4: 2025-09 | L4: 45917.122 | M4: 146.6 | N4: 1
A5: 4 | B5: Lumen Schools | C5: Standard | D5: UK & Ireland | E5: Report Request | F5: James Whitfield | G5: Technical Services | H5: Medium | I5: Closed | J5: 45968.738 | K5: 2025-11 | L5: 45969.803 | M5: 25.6 | N5: 1
A6: 5 | B6: Fjord Systems | C6: Standard | D6: EMEA | E6: Bug | F6: Dev Patel | G6: Service Desk | H6: Medium | I6: Resolved | J6: 46023.882 | K6: 2026-01 | L6: 46024.329 | M6: 10.7 | N6: 1
A7: 6 | B7: Iris Insurance | C7: Business | D7: EMEA | E7: Bug | F7: Dev Patel | G7: Service Desk | H7: High | I7: Closed | J7: 45953.166 | K7: 2025-10 | L7: 45953.841 | M7: 16.2 | N7: 1
A8: 7 | B8: Nordic Freight | C8: Standard | D8: EMEA | E8: Performance | F8: Marcus Boateng | G8: Service Desk | H8: Medium | I8: Closed | J8: 46142.953 | K8: 2026-04 | L8: 46144.101 | M8: 27.5 | N8: 1
A9: 8 | B9: Kite Energy | C9: Business | D9: UK & Ireland | E9: Bug | F9: James Whitfield | G9: Technical Services | H9: Medium | I9: Resolved | J9: 46164.507 | K9: 2026-05 | L9: 46165.304 | M9: 19.1 | N9: 1
A10: 9 | B10: Orchard Pharma | C10: Business | D10: North America | E10: How-To Question | F10: Priya Sharma | G10: Technical Services | H10: Low | I10: Resolved | J10: 46056.581 | K10: 2026-02 | L10: 46056.967 | M10: 9.3 | N10: 1
A11: 10 | B11: Bristol Logistics | C11: Business | D11: UK & Ireland | E11: Performance | F11: Marcus Boateng | G11: Service Desk | H11: Low | I11: Closed | J11: 45987.359 | K11: 2025-11 | L11: 45993.775 | M11: 154 | N11: 1
A12: 11 | B12: Cornwall Foods | C12: Standard | D12: UK & Ireland | E12: Performance | F12: Marcus Boateng | G12: Service Desk | H12: Medium | I12: Resolved | J12: 46025.178 | K12: 2026-01 | L12: 46026.426 | M12: 30 | N12: 1
A13: 12 | B13: Iris Insurance | C13: Business | D13: EMEA | E13: Report Request | F13: Priya Sharma | G13: Technical Services | H13: Low | I13: Resolved | J13: 46150.302 | K13: 2026-05 | L13: 46151.562 | M13: 30.2 | N13: 1
A14: 13 | B14: Bristol Logistics | C14: Business | D14: UK & Ireland | E14: Report Request | F14: Marcus Boateng | G14: Service Desk | H14: Medium | I14: Closed | J14: 45938.614 | K14: 2025-10 | L14: 45941.53 | M14: 70 | N14: 1
A15: 14 | B15: Kite Energy | C15: Business | D15: UK & Ireland | E15: Data Issue | F15: Elena Kovacs | G15: Service Desk | H15: High | I15: Resolved | J15: 46022.204 | K15: 2025-12 | L15: 46022.662 | M15: 11 | N15: 1
... A21: 20 | B21: Harbour Hotels | C21: Standard | D21: UK & Ireland | E21: Data Issue | F21: Elena Kovacs | G21: Service Desk | H21: High | I21: Closed | J21: 46035.981 | K21: 2026-01 | L21: 46036.554 | M21: 13.7 | N21: 1
A22: 21 | B22: Bristol Logistics | C22: Business | D22: UK & Ireland | E22: Data Issue | F22: Elena Kovacs | G22: Service Desk | H22: High | I22: Open | J22: 46049.79 | K22: 2026-01 | N22: 0 | O22: Open > 30 days
A23: 22 | B23: Everton Health | C23: Enterprise | D23: UK & Ireland | E23: Report Request | F23: Dev Patel | G23: Service Desk | H23: Medium | I23: Closed | J23: 46060.498 | K23: 2026-02 | L23: 46062.247 | M23: 42 | N23: 1
A24: 23 | B24: Metro Transport | C24: Enterprise | D24: EMEA | E24: Report Request | F24: Elena Kovacs | G24: Service Desk | H24: Low | I24: In Progress | J24: 46077.848 | K24: 2026-02 | N24: 0
A25: 24 | B25: Nordic Freight | C25: Standard | D25: EMEA | E25: Data Issue | F25: Unassigned | G25: Unassigned | H25: Medium | I25: Open | J25: 46144.835 | K25: 2026-05 | N25: 0 | O25: Open > 30 days
A26: 25 | B26: DataFirst GmbH | C26: Business | D26: EMEA | E26: Performance | F26: James Whitfield | G26: Technical Services | H26: Low | I26: Closed | J26: 46077.994 | K26: 2026-02 | L26: 46080.065 | M26: 49.7 | N26: 1
A27: 26 | B27: Harbour Hotels | C27: Standard | D27: UK & Ireland | E27: How-To Question | F27: Unassigned | G27: Unassigned | H27: Medium | I27: Open | J27: 46145.206 | K27: 2026-05 | N27: 0 | O27: Open > 30 days
A28: 27 | B28: Orchard Pharma | C28: Business | D28: North America | E28: Performance | F28: Marcus Boateng | G28: Service Desk | H28: Low | I28: Closed | J28: 46095.397 | K28: 2026-03 | L28: 46098.304 | M28: 69.8 | N28: 1
A29: 28 | B29: Acme Retail | C29: Enterprise | D29: UK & Ireland | E29: Report Request | F29: Marcus Boateng | G29: Service Desk | H29: Low | I29: Resolved | J29: 46023.385 | K29: 2026-01 | L29: 46028.312 | M29: 118.2 | N29: 1
A30: 29 | B30: Kite Energy | C30: Business | D30: UK & Ireland | E30: Report Request | F30: James Whitfield | G30: Technical Services | H30: Medium | I30: Closed | J30: 46103.781 | K30: 2026-03 | L30: 46105.553 | M30: 42.5 | N30: 1
A31: 30 | B31: Acme Retail | C31: Enterprise | D31: UK & Ireland | E31: Data Issue | F31: Sofia Lindqvist | G31: Service Desk | H31: Low | I31: Closed | J31: 45869.314 | K31: 2025-07 | L31: 45876.046 | M31: 161.6 | N31: 1
A32: 31 | B32: Bristol Logistics | C32: Business | D32: UK & Ireland | E32: How-To Question | F32: James Whitfield | G32: Technical Services | H32: Low | I32: Resolved | J32: 46167.012 | K32: 2026-05 | L32: 46173.613 | M32: 158.4 | N32: 1
A33: 32 | B33: Juno Media | C33: Standard | D33: North America | E33: Data Issue | F33: Sofia Lindqvist | G33: Service Desk | H33: Medium | I33: Closed | J33: 46156.802 | K33: 2026-05 | L33: 46157.808 | M33: 24.1 | N33: 1
A34: 33 | B34: DataFirst GmbH | C34: Business | D34: EMEA | E34: Bug | F34: Marcus Boateng | G34: Service Desk | H34: Low | I34: In Progress | J34: 45928.298 | K34: 2025-09 | N34: 0
A35: 34 | B35: Acme Retail | C35: Enterprise | D35: UK & Ireland | E35: Report Request | F35: Elena Kovacs | G35: Service Desk | H35: High | I35: Open | J35: 46143.697 | K35: 2026-05 | N35: 0 | O35: Open > 30 days
A36: 35 | B36: Orchard Pharma | C36: Business | D36: North America | E36: Data Issue | F36: James Whitfield | G36: Technical Services | H36: Low | I36: Closed | J36: 46038.618 | K36: 2026-01 | L36: 46042.497 | M36: 93.1 | N36: 1
A37: 36 | B37: Acme Retail | C37: Enterprise | D37: UK & Ireland | E37: How-To Question | F37: Priya Sharma | G37: Technical Services | H37: Medium | I37: Resolved | J37: 45998.499 | K37: 2025-12 | L37: 45998.974 | M37: 11.4 | N37: 1
A38: 37 | B38: Lumen Schools | C38: Standard | D38: UK & Ireland | E38: How-To Question | F38: Sofia Lindqvist | G38: Service Desk | H38: Low | I38: Closed | J38: 46103.307 | K38: 2026-03 | L38: 46105.817 | M38: 60.2 | N38: 1
A39: 38 | B39: Iris Insurance | C39: Business | D39: EMEA | E39: Report Request | F39: Priya Sharma | G39: Technical Services | H39: High | I39: Resolved | J39: 46033.64 | K39: 2026-01 | L39: 46034.087 | M39: 10.7 | N39: 1
A40: 39 | B40: Fjord Systems | C40: Standard | D40: EMEA | E40: Performance | F40: Marcus Boateng | G40: Service Desk | H40: Medium | I40: Closed | J40: 46025.75 | K40: 2026-01 | N40: 1 | O40: Resolved but no ResolvedAt
A41: 40 | B41: Orchard Pharma | C41: Business | D41: North America | E41: Performance | F41: Sofia Lindqvist | G41: Service Desk | H41: Medium | I41: Resolved | J41: 46190.265 | K41: 2026-06 | L41: 46191.602 | M41: 32.1 | N41: 1
A42: 41 | B42: Orchard Pharma | C42: Business | D42: North America | E42: Data Issue | F42: James Whitfield | G42: Technical Services | H42: Medium | I42: Closed | J42: 45955.951 | K42: 2025-10 | L42: 45957.066 | M42: 26.8 | N42: 1
A43: 42 | B43: Juno Media | C43: Standard | D43: North America | E43: Performance | F43: James Whitfield | G43: Technical Services | H43: Medium | I43: Resolved | J43: 46044.113 | K43: 2026-01 | L43: 46044.269 | M43: 3.7 | N43: 1
A44: 43 | B44: Metro Transport | C44: Enterprise | D44: EMEA | E44: Report Request | F44: Dev Patel | G44: Service Desk | H44: High | I44: Closed | J44: 46035.79 | K44: 2026-01 | L44: 46036.668 | M44: 21.1 | N44: 1
A45: 44 | B45: DataFirst GmbH | C45: Business | D45: EMEA | E45: Report Request | F45: James Whitfield | G45: Technical Services | H45: Low | I45: Closed | J45: 45961.887 | K45: 2025-10 | L45: 45966.564 | M45: 112.2 | N45: 1
A46: 45 | B46: Nordic Freight | C46: Standard | D46: EMEA | E46: Data Issue | F46: Sofia Lindqvist | G46: Service Desk | H46: Low | I46: Closed | J46: 46013.248 | K46: 2025-12 | L46: 46020.119 | M46: 164.9 | N46: 1
A47: 46 | B47: Bristol Logistics | C47: Business | D47: UK & Ireland | E47: Bug | F47: Elena Kovacs | G47: Service Desk | H47: High | I47: Closed | J47: 46086.472 | K47: 2026-03 | L47: 46087.085 | M47: 14.7 | N47: 1
A48: 47 | B48: Granite Bank | C48: Enterprise | D48: North America | E48: How-To Question | F48: Sofia Lindqvist | G48: Service Desk | H48: Low | I48: Closed | J48: 46132.29 | K48: 2026-04 | L48: 46132.76 | M48: 11.3 | N48: 1
A49: 48 | B49: Orchard Pharma | C49: Business | D49: North America | E49: How-To Question | F49: Priya Sharma | G49: Technical Services | H49: Medium | I49: Closed | J49: 46073.024 | K49: 2026-02 | L49: 46075.793 | M49: 66.5 | N49: 1
A50: 49 | B50: Lumen Schools | C50: Standard | D50: UK & Ireland | E50: Bug | F50: Elena Kovacs | G50: Service Desk | H50: Low | I50: Resolved | J50: 45991.286 | K50: 2025-11 | L50: 45993.473 | M50: 52.5 | N50: 1
A51: 50 | B51: Kite Energy | C51: Business | D51: UK & Ireland | E51: Report Request | F51: Elena Kovacs | G51: Service Desk | H51: Low | I51: Resolved | J51: 46089.778 | K51: 2026-03 | L51: 46095.642 | M51: 140.7 | N51: 1
A52: 51 | B52: Granite Bank | C52: Enterprise | D52: North America | E52: How-To Question | F52: Marcus Boateng | G52: Service Desk | H52: Medium | I52: Closed | J52: 45981.846 | K52: 2025-11 | L52: 45983.42 | M52: 37.8 | N52: 1
... A65: 64 | B65: Bristol Logistics | C65: Business | D65: UK & Ireland | E65: Report Request | F65: James Whitfield | G65: Technical Services | H65: High | I65: Resolved | J65: 46117.687 | K65: 2026-04 | L65: 46118.092 | M65: 9.7 | N65: 1
A66: 65 | B66: Fjord Systems | C66: Standard | D66: EMEA | E66: Report Request | F66: Marcus Boateng | G66: Service Desk | H66: Low | I66: Resolved | J66: 46013.88 | K66: 2025-12 | N66: 1 | O66: Resolved but no ResolvedAt
A67: 66 | B67: Acme Retail | C67: Enterprise | D67: UK & Ireland | E67: Bug | F67: Dev Patel | G67: Service Desk | H67: High | I67: Resolved | J67: 46053.227 | K67: 2026-01 | L67: 46053.298 | M67: 1.7 | N67: 1
A68: 67 | B68: Juno Media | C68: Standard | D68: North America | E68: Performance | F68: Sofia Lindqvist | G68: Service Desk | H68: Medium | I68: In Progress | J68: 46042.797 | K68: 2026-01 | N68: 0
A69: 68 | B69: Lumen Schools | C69: Standard | D69: UK & Ireland | E69: Bug | F69: Sofia Lindqvist | G69: Service Desk | H69: Medium | I69: Closed | J69: 45947.879 | K69: 2025-10 | L69: 45950.058 | M69: 52.3 | N69: 1
A70: 69 | B70: Everton Health | C70: Enterprise | D70: UK & Ireland | E70: Data Issue | F70: Sofia Lindqvist | G70: Service Desk | H70: Medium | I70: Resolved | J70: 46197.802 | K70: 2026-06 | L70: 46200.68 | M70: 69.1 | N70: 1
A71: 70 | B71: Bristol Logistics | C71: Business | D71: UK & Ireland | E71: How-To Question | F71: Dev Patel | G71: Service Desk | H71: Medium | I71: In Progress | J71: 46039.662 | K71: 2026-01 | N71: 0
A72: 71 | B72: Metro Transport | C72: Enterprise | D72: EMEA | E72: How-To Question | F72: Marcus Boateng | G72: Service Desk | H72: Medium | I72: Closed | J72: 46186.594 | K72: 2026-06 | L72: 46186.879 | M72: 6.8 | N72: 1
A73: 72 | B73: Nordic Freight | C73: Standard | D73: EMEA | E73: Report Request | F73: Unassigned | G73: Unassigned | H73: Medium | I73: In Progress | J73: 45859.547 | K73: 2025-07 | N73: 0 | O73: In Progress, no agent
A74: 73 | B74: Lumen Schools | C74: Standard | D74: UK & Ireland | E74: Performance | F74: Sofia Lindqvist | G74: Service Desk | H74: Medium | I74: Closed | J74: 45899.388 | K74: 2025-08 | L74: 45900.259 | M74: 20.9 | N74: 1
A75: 74 | B75: Metro Transport | C75: Enterprise | D75: EMEA | E75: Report Request | F75: Dev Patel | G75: Service Desk | H75: Medium | I75: Closed | J75: 45877.99 | K75: 2025-08 | L75: 45879.013 | M75: 24.6 | N75: 1
A76: 75 | B76: Everton Health | C76: Enterprise | D76: UK & Ireland | E76: Report Request | F76: Sofia Lindqvist | G76: Service Desk | H76: Medium | I76: Resolved | J76: 46038.924 | K76: 2026-01 | L76: 46040.113 | M76: 28.5 | N76: 1
A77: 76 | B77: Cornwall Foods | C77: Standard | D77: UK & Ireland | E77: Report Request | F77: Elena Kovacs | G77: Service Desk | H77: Low | I77: Closed | J77: 46062.04 | K77: 2026-02 | L77: 46068.222 | M77: 148.4 | N77: 1
A78: 77 | B78: Iris Insurance | C78: Business | D78: EMEA | E78: Data Issue | F78: Marcus Boateng | G78: Service Desk | H78: Medium | I78: In Progress | J78: 46077.377 | K78: 2026-02 | N78: 0
A79: 78 | B79: Lumen Schools | C79: Standard | D79: UK & Ireland | E79: Report Request | F79: Priya Sharma | G79: Technical Services | H79: High | I79: Closed | J79: 45859.095 | K79: 2025-07 | L79: 45859.349 | M79: 6.1 | N79: 1
A80: 79 | B80: Kite Energy | C80: Business | D80: UK & Ireland | E80: How-To Question | F80: Sofia Lindqvist | G80: Service Desk | H80: Low | I80: Closed | J80: 45947.788 | K80: 2025-10 | L80: 45954.765 | M80: 167.4 | N80: 1
A81: 80 | B81: Lumen Schools | C81: Standard | D81: UK & Ireland | E81: Report Request | F81: James Whitfield | G81: Technical Services | H81: High | I81: Closed | J81: 46019.225 | K81: 2025-12 | L81: 46019.451 | M81: 5.4 | N81: 1
A82: 81 | B82: Metro Transport | C82: Enterprise | D82: EMEA | E82: Performance | F82: Marcus Boateng | G82: Service Desk | H82: Low | I82: Closed | J82: 46077.024 | K82: 2026-02 | L82: 46081.22 | M82: 100.7 | N82: 1
A83: 82 | B83: Everton Health | C83: Enterprise | D83: UK & Ireland | E83: Data Issue | F83: Elena Kovacs | G83: Service Desk | H83: Low | I83: Closed | J83: 46075.148 | K83: 2026-02 | L83: 46075.411 | M83: 6.3 | N83: 1
A84: 83 | B84: Acme Retail | C84: Enterprise | D84: UK & Ireland | E84: Data Issue | F84: James Whitfield | G84: Technical Services | H84: Medium | I84: Resolved | J84: 46003.773 | K84: 2025-12 | L84: 46006.052 | M84: 54.7 | N84: 1
A85: 84 | B85: Juno Media | C85: Standard | D85: North America | E85: Bug | F85: Elena Kovacs | G85: Service Desk | H85: Low | I85: Closed | J85: 45874.696 | K85: 2025-08 | L85: 45875.214 | M85: 12.4 | N85: 1
A86: 85 | B86: Bristol Logistics | C86: Business | D86: UK & Ireland | E86: Data Issue | F86: Sofia Lindqvist | G86: Service Desk | H86: Medium | I86: Closed | J86: 45924.714 | K86: 2025-09 | L86: 45924.954 | M86: 5.8 | N86: 1
A87: 86 | B87: Everton Health | C87: Enterprise | D87: UK & Ireland | E87: Data Issue | F87: Sofia Lindqvist | G87: Service Desk | H87: Medium | I87: In Progress | J87: 46035.773 | K87: 2026-01 | N87: 0
A88: 87 | B88: DataFirst GmbH | C88: Business | D88: EMEA | E88: How-To Question | F88: Marcus Boateng | G88: Service Desk | H88: Low | I88: Closed | J88: 45939.517 | K88: 2025-10 | L88: 45943.706 | M88: 100.5 | N88: 1
A89: 88 | B89: Juno Media | C89: Standard | D89: North America | E89: Data Issue | F89: James Whitfield | G89: Technical Services | H89: Medium | I89: Resolved | J89: 46144.241 | K89: 2026-05 | L89: 46145.096 | M89: 20.5 | N89: 1
A90: 89 | B90: Cornwall Foods | C90: Standard | D90: UK & Ireland | E90: How-To Question | F90: Dev Patel | G90: Service Desk | H90: Medium | I90: In Progress | J90: 46161.84 | K90: 2026-05 | N90: 0
A91: 90 | B91: Acme Retail | C91: Enterprise | D91: UK & Ireland | E91: Performance | F91: Dev Patel | G91: Service Desk | H91: Medium | I91: Resolved | J91: 46006.709 | K91: 2025-12 | L91: 46007 | M91: 7 | N91: 1
A92: 91 | B92: Metro Transport | C92: Enterprise | D92: EMEA | E92: How-To Question | F92: Sofia Lindqvist | G92: Service Desk | H92: Low | I92: Closed | J92: 46072.453 | K92: 2026-02 | L92: 46073.638 | M92: 28.4 | N92: 1
A93: 92 | B93: Bristol Logistics | C93: Business | D93: UK & Ireland | E93: Data Issue | F93: Sofia Lindqvist | G93: Service Desk | H93: Medium | I93: Resolved | J93: 46095.679 | K93: 2026-03 | L93: 46097.423 | M93: 41.8 | N93: 1
A94: 93 | B94: Harbour Hotels | C94: Standard | D94: UK & Ireland | E94: Bug | F94: Sofia Lindqvist | G94: Service Desk | H94: Medium | I94: Resolved | J94: 45923.403 | K94: 2025-09 | L94: 45924.763 | M94: 32.6 | N94: 1
A95: 94 | B95: Lumen Schools | C95: Standard | D95: UK & Ireland | E95: Bug | F95: Dev Patel | G95: Service Desk | H95: Medium | I95: Open | J95: 46034.188 | K95: 2026-01 | N95: 0 | O95: Open > 30 days
A96: 95 | B96: Juno Media | C96: Standard | D96: North America | E96: Data Issue | F96: James Whitfield | G96: Technical Services | H96: Medium | I96: Closed | J96: 46020.249 | K96: 2025-12 | L96: 46022.232 | M96: 47.6 | N96: 1
A97: 96 | B97: Juno Media | C97: Standard | D97: North America | E97: Report Request | F97: Marcus Boateng | G97: Service Desk | H97: Low | I97: Resolved | J97: 45858.437 | K97: 2025-07 | L97: 45860.881 | M97: 58.7 | N97: 1
A98: 97 | B98: Fjord Systems | C98: Standard | D98: EMEA | E98: Report Request | F98: Marcus Boateng | G98: Service Desk | H98: Medium | I98: Closed | J98: 45855.711 | K98: 2025-07 | L98: 45857.399 | M98: 40.5 | N98: 1
A99: 98 | B99: Everton Health | C99: Enterprise | D99: UK & Ireland | E99: Bug | F99: Marcus Boateng | G99: Service Desk | H99: Medium | I99: Resolved | J99: 46132.089 | K99: 2026-04 | N99: 1 | O99: Resolved but no ResolvedAt
A100: 99 | B100: Harbour Hotels | C100: Standard | D100: UK & Ireland | E100: Report Request | F100: Elena Kovacs | G100: Service Desk | H100: Medium | I100: Closed | J100: 46177.03 | K100: 2026-06 | L100: 46178.567 | M100: 36.9 | N100: 1
A101: 100 | B101: DataFirst GmbH | C101: Business | D101: EMEA | E101: Bug | F101: Marcus Boateng | G101: Service Desk | H101: Medium | I101: Resolved | J101: 46121.099 | K101: 2026-04 | L101: 46122.596 | M101: 35.9 | N101: 1
A102: 101 | B102: Metro Transport | C102: Enterprise | D102: EMEA | E102: Performance | F102: Priya Sharma | G102: Technical Services | H102: Medium | I102: Closed | J102: 46101.173 | K102: 2026-03 | L102: 46101.528 | M102: 8.5 | N102: 1
A103: 102 | B103: Harbour Hotels | C103: Standard | D103: UK & Ireland | E103: Data Issue | F103: Dev Patel | G103: Service Desk | H103: Low | I103: Closed | J103: 46104.382 | K103: 2026-03 | L103: 46109.369 | M103: 119.7 | N103: 1
A104: 103 | B104: Harbour Hotels | C104: Standard | D104: UK & Ireland | E104: Performance | F104: Marcus Boateng | G104: Service Desk | H104: Low | I104: Closed | J104: 45883.878 | K104: 2025-08 | L104: 45888.141 | M104: 102.3 | N104: 1
A105: 104 | B105: Nordic Freight | C105: Standard | D105: EMEA | E105: Data Issue | F105: Marcus Boateng | G105: Service Desk | H105: Low | I105: Resolved | J105: 46015.343 | K105: 2025-12 | L105: 46020.892 | M105: 133.2 | N105: 1
A106: 105 | B106: Everton Health | C106: Enterprise | D106: UK & Ireland | E106: Bug | F106: Marcus Boateng | G106: Service Desk | H106: Medium | I106: Resolved | J106: 45859.955 | K106: 2025-07 | L106: 45861.045 | M106: 26.2 | N106: 1
A107: 106 | B107: Granite Bank | C107: Enterprise | D107: North America | E107: Report Request | F107: Dev Patel | G107: Service Desk | H107: Low | I107: Resolved | J107: 45982.189 | K107: 2025-11 | L107: 45984.973 | M107: 66.8 | N107: 1
A108: 107 | B108: Acme Retail | C108: Enterprise | D108: UK & Ireland | E108: Bug | F108: Marcus Boateng | G108: Service Desk | H108: Low | I108: Resolved | J108: 45872.09 | K108: 2025-08 | L108: 45876.791 | M108: 112.8 | N108: 1
A109: 108 | B109: Harbour Hotels | C109: Standard | D109: UK & Ireland | E109: Data Issue | F109: Sofia Lindqvist | G109: Service Desk | H109: Low | I109: Closed | J109: 46124.571 | K109: 2026-04 | L109: 46125.423 | M109: 20.5 | N109: 1
A110: 109 | B110: Iris Insurance | C110: Business | D110: EMEA | E110: Report Request | F110: Marcus Boateng | G110: Service Desk | H110: Medium | I110: Resolved | J110: 46205.324 | K110: 2026-07 | L110: 46208.237 | M110: 69.9 | N110: 1
A111: 110 | B111: Fjord Systems | C111: Standard | D111: EMEA | E111: How-To Question | F111: Elena Kovacs | G111: Service Desk | H111: Medium | I111: Resolved | J111: 45927.062 | K111: 2025-09 | L111: 45929.652 | M111: 62.2 | N111: 1
... A118: 117 | B118: Nordic Freight | C118: Standard | D118: EMEA | E118: Report Request | F118: Sofia Lindqvist | G118: Service Desk | H118: Low | I118: Closed | J118: 46138.838 | K118: 2026-04 | L118: 46141.026 | M118: 52.5 | N118: 1
A119: 118 | B119: Nordic Freight | C119: Standard | D119: EMEA | E119: Report Request | F119: Unassigned | G119: Unassigned | H119: Medium | I119: Open | J119: 46016.63 | K119: 2025-12 | N119: 0 | O119: Open > 30 days
A120: 119 | B120: Orchard Pharma | C120: Business | D120: North America | E120: How-To Question | F120: Elena Kovacs | G120: Service Desk | H120: Medium | I120: Resolved | J120: 45854.794 | K120: 2025-07 | L120: 45855.549 | M120: 18.1 | N120: 1
A121: 120 | B121: Kite Energy | C121: Business | D121: UK & Ireland | E121: Performance | F121: Dev Patel | G121: Service Desk | H121: Medium | I121: Resolved | J121: 46033.999 | K121: 2026-01 | L121: 46036.068 | M121: 49.7 | N121: 1
A122: 121 | B122: Orchard Pharma | C122: Business | D122: North America | E122: Data Issue | F122: Priya Sharma | G122: Technical Services | H122: Medium | I122: Resolved | J122: 45991.542 | K122: 2025-11 | L122: 45993.762 | M122: 53.3 | N122: 1
A123: 122 | B123: Fjord Systems | C123: Standard | D123: EMEA | E123: Report Request | F123: Sofia Lindqvist | G123: Service Desk | H123: Medium | I123: Closed | J123: 46088.603 | K123: 2026-03 | L123: 46089.754 | M123: 27.6 | N123: 1
...

Sheet PivotSummary
A1: Pivot Summaries (built from Cleaned Data)
A4: Tickets by Status | D4: Avg Resolution Time by Priority | G4: Monthly Ticket Trend
A5: Status | B5: Tickets | D5: Priority | E5: Avg Hours to Resolve | G5: Month | H5: Tickets
A6: Open | B6: =COUNTIF('Cleaned Data'!$I$2:$I$3001,A6) -> 228 | D6: High | E6: =IFERROR(ROUND(AVERAGEIFS('Cleaned Data'!$M$2:$M$3001,'Cleaned Data'!$H$2:$H$3001,D6),1),0) -> 12.6 | G6: 2025-07 | H6: =COUNTIF('Cleaned Data'!$K$2:$K$3001,G6) -> 154
A7: In Progress | B7: =COUNTIF('Cleaned Data'!$I$2:$I$3001,A7) -> 237 | D7: Medium | E7: =IFERROR(ROUND(AVERAGEIFS('Cleaned Data'!$M$2:$M$3001,'Cleaned Data'!$H$2:$H$3001,D7),1),0) -> 37.3 | G7: 2025-08 | H7: =COUNTIF('Cleaned Data'!$K$2:$K$3001,G7) -> 241
A8: Resolved | B8: =COUNTIF('Cleaned Data'!$I$2:$I$3001,A8) -> 1196 | D8: Low | E8: =IFERROR(ROUND(AVERAGEIFS('Cleaned Data'!$M$2:$M$3001,'Cleaned Data'!$H$2:$H$3001,D8),1),0) -> 82.8 | G8: 2025-09 | H8: =COUNTIF('Cleaned Data'!$K$2:$K$3001,G8) -> 245
A9: Closed | B9: =COUNTIF('Cleaned Data'!$I$2:$I$3001,A9) -> 1339 | G9: 2025-10 | H9: =COUNTIF('Cleaned Data'!$K$2:$K$3001,G9) -> 247
A10: Total | B10: =SUM(B6:B9) -> 3000 | D10: Tickets by Customer Tier | G10: 2025-11 | H10: =COUNTIF('Cleaned Data'!$K$2:$K$3001,G10) -> 259
D11: Tier | E11: Tickets | G11: 2025-12 | H11: =COUNTIF('Cleaned Data'!$K$2:$K$3001,G11) -> 252
A12: Tickets by Category | D12: Standard | E12: =COUNTIF('Cleaned Data'!$C$2:$C$3001,D12) -> 1212 | G12: 2026-01 | H12: =COUNTIF('Cleaned Data'!$K$2:$K$3001,G12) -> 251
A13: Category | B13: Tickets | D13: Business | E13: =COUNTIF('Cleaned Data'!$C$2:$C$3001,D13) -> 965 | G13: 2026-02 | H13: =COUNTIF('Cleaned Data'!$K$2:$K$3001,G13) -> 211
A14: How-To Question | B14: =COUNTIF('Cleaned Data'!$E$2:$E$3001,A14) -> 637 | D14: Enterprise | E14: =COUNTIF('Cleaned Data'!$C$2:$C$3001,D14) -> 823 | G14: 2026-03 | H14: =COUNTIF('Cleaned Data'!$K$2:$K$3001,G14) -> 255
A15: Report Request | B15: =COUNTIF('Cleaned Data'!$E$2:$E$3001,A15) -> 628 | G15: 2026-04 | H15: =COUNTIF('Cleaned Data'!$K$2:$K$3001,G15) -> 271
A16: Performance | B16: =COUNTIF('Cleaned Data'!$E$2:$E$3001,A16) -> 584 | G16: 2026-05 | H16: =COUNTIF('Cleaned Data'!$K$2:$K$3001,G16) -> 260
A17: Data Issue | B17: =COUNTIF('Cleaned Data'!$E$2:$E$3001,A17) -> 582 | G17: 2026-06 | H17: =COUNTIF('Cleaned Data'!$K$2:$K$3001,G17) -> 258
A18: Bug | B18: =COUNTIF('Cleaned Data'!$E$2:$E$3001,A18) -> 569 | G18: 2026-07 | H18: =COUNTIF('Cleaned Data'!$K$2:$K$3001,G18) -> 96
A19: Total | B19: =SUM(B14:B18) -> 3000

Sheet Notes
A1: Notes
A4: 1. DATA SOURCE
A5: Extracted from SQL Server database 'TicketTracker' (dbo.Tickets, dbo.Customers,
A6: dbo.Agents, dbo.Categories). Raw export is on the 'Raw Data (SQL export)' tab.
A8: 2. CLEANING & TRANSFORMATION (‘Cleaned Data’ tab)
A9: • Joined the lookup tables so IDs became readable names (Customer, Agent, Category).
A10: • Converted CreatedAt / ResolvedAt from text to real dates.
A11: • Added helper columns: Month, HoursToResolve, IsResolved.
A12: • Added a DataQualityFlag column that highlights rows breaking business rules
A13: (resolved with no resolved date; in-progress with no agent; open > 30 days).
A14: • Unassigned agents relabelled 'Unassigned' instead of blank.
A16: 3. REPORTING
... A27: Prepared as a portfolio piece to demonstrate the SQL→Excel reporting workflow.
